twill3/__init__.py
twill3/browser.py
twill3/commands.py
twill3/errors.py
twill3/namespaces.py
twill3/parse.py
twill3/shell.py
twill3/unit.py
twill3/utils.py
twill3/wsgi_intercept.py
twill3/extensions/__init__.py
twill3/extensions/argparse.py
twill3/extensions/check_links.py
twill3/extensions/csv_iterate.py
twill3/extensions/dirstack.py
twill3/extensions/dns_check.py
twill3/extensions/formfill.py
twill3/extensions/mailman_sf.py
twill3/extensions/require.py
twill3/extensions/test_extensions.py
twill3/extensions/match_parse/__init__.py
twill3/extensions/match_parse/test-match_parse.py
twill3/other_packages/__init__.py
twill3/other_packages/pyparsing.py
twill3/other_packages/subprocess.py
twill3/other_packages/_mechanize_dist/ClientForm.py
twill3/other_packages/_mechanize_dist/__init__.py
twill3/other_packages/_mechanize_dist/_auth.py
twill3/other_packages/_mechanize_dist/_beautifulsoup.py
twill3/other_packages/_mechanize_dist/_clientcookie.py
twill3/other_packages/_mechanize_dist/_debug.py
twill3/other_packages/_mechanize_dist/_gzip.py
twill3/other_packages/_mechanize_dist/_headersutil.py
twill3/other_packages/_mechanize_dist/_html.py
twill3/other_packages/_mechanize_dist/_http.py
twill3/other_packages/_mechanize_dist/_lwpcookiejar.py
twill3/other_packages/_mechanize_dist/_mechanize.py
twill3/other_packages/_mechanize_dist/_mozillacookiejar.py
twill3/other_packages/_mechanize_dist/_msiecookiejar.py
twill3/other_packages/_mechanize_dist/_opener.py
twill3/other_packages/_mechanize_dist/_pullparser.py
twill3/other_packages/_mechanize_dist/_request.py
twill3/other_packages/_mechanize_dist/_response.py
twill3/other_packages/_mechanize_dist/_rfc3986.py
twill3/other_packages/_mechanize_dist/_seek.py
twill3/other_packages/_mechanize_dist/_upgrade.py
twill3/other_packages/_mechanize_dist/_urllib2.py
twill3/other_packages/_mechanize_dist/_useragent.py
twill3/other_packages/_mechanize_dist/_util.py
twill3-0.11.2.data/scripts/twill
twill3-0.11.2.dist-info/LICENSE
twill3-0.11.2.dist-info/METADATA
twill3-0.11.2.dist-info/WHEEL
twill3-0.11.2.dist-info/top_level.txt
twill3-0.11.2.dist-info/RECORD
