Metadata-Version: 2.1
Name: twill3
Version: 0.11.2
Summary: Update twill for Python3 compatibility
Home-page: UNKNOWN
Author: Jon Froiland
Author-email: jon.froiland@gmail.com
License: UNKNOWN
Platform: UNKNOWN
Classifier: Programming Language :: Python :: 3.6
Classifier: License :: OSI Approved :: MIT License
Classifier: Operating System :: OS Independent
Requires-Dist: lxml
Requires-Dist: requests
Requires-Dist: pyparsing
